pyafv/__init__.py
pyafv/_version.py
pyafv/backend.py
pyafv/cell_geom.cpython-310-aarch64-linux-gnu.so
pyafv/cell_geom.cpython-311-aarch64-linux-gnu.so
pyafv/cell_geom.cpython-312-aarch64-linux-gnu.so
pyafv/cell_geom.cpython-313-aarch64-linux-gnu.so
pyafv/cell_geom_fallback.py
pyafv/finite_voronoi.py
pyafv/physical_params.py
pyafv/calibrate/__init__.py
pyafv/calibrate/core.py
pyafv/calibrate/deformable_polygon.py
pyafv-0.4.3.dist-info/METADATA
pyafv-0.4.3.dist-info/WHEEL
pyafv-0.4.3.dist-info/RECORD
pyafv-0.4.3.dist-info/licenses/LICENSE
