Metadata-Version: 2.4
Name: pyafv
Version: 0.4.3
Summary: Python implementation of the active-finite-Voronoi (AFV) model
Project-URL: Homepage, https://pyafv.github.io
Project-URL: Download, https://pypi.org/project/pyafv/#files
Project-URL: Source Code, https://github.com/wwang721/pyafv
Project-URL: Documentation, https://pyafv.readthedocs.io/
Project-URL: Changelog, https://github.com/wwang721/pyafv/releases/latest
Author: Wei Wang
Author-email: ww000721@gmail.com
License-Expression: MIT
License-File: LICENSE
Keywords: biological-modeling,cellular-patterns,voronoi-model
Classifier: Development Status :: 4 - Beta
Classifier: Intended Audience :: Developers
Classifier: Intended Audience :: Science/Research
Classifier: Operating System :: OS Independent
Classifier: Programming Language :: Python :: 3
Classifier: Programming Language :: Python :: 3.10
Classifier: Programming Language :: Python :: 3.11
Classifier: Programming Language :: Python :: 3.12
Classifier: Programming Language :: Python :: 3.13
Classifier: Programming Language :: Python :: 3.14
Classifier: Topic :: Scientific/Engineering
Requires-Python: <3.15,>=3.10
Requires-Dist: matplotlib>=3.8.4
Requires-Dist: numpy>=1.26.4
Requires-Dist: scipy>=1.13.1
Provides-Extra: examples
Requires-Dist: ipywidgets>=8.1.5; extra == 'examples'
Requires-Dist: jupyter>=1.1.0; extra == 'examples'
Requires-Dist: tqdm>=4.67.1; extra == 'examples'
